[{"name": "02-24", "rooms_1": 0, "rooms_2": 0, "rooms_3": 0, "rooms_4": 0}, {"name": "03-02", "rooms_1": 5, "rooms_2": 18, "rooms_3": 49, "rooms_4": 16}, {"name": "03-09", "rooms_1": 24, "rooms_2": 58, "rooms_3": 64, "rooms_4": 33}, {"name": "03-16", "rooms_1": 32, "rooms_2": 51, "rooms_3": 71, "rooms_4": 67}, {"name": "03-23", "rooms_1": 54, "rooms_2": 136, "rooms_3": 202, "rooms_4": 86}, {"name": "03-30", "rooms_1": 33, "rooms_2": 166, "rooms_3": 255, "rooms_4": 142}, {"name": "04-06", "rooms_1": 10, "rooms_2": 22, "rooms_3": 20, "rooms_4": 22}]