[{"name": "02-24", "rooms_1": 3, "rooms_2": 24, "rooms_3": 5, "rooms_4": 1}, {"name": "03-02", "rooms_1": 17, "rooms_2": 80, "rooms_3": 36, "rooms_4": 5}, {"name": "03-09", "rooms_1": 38, "rooms_2": 155, "rooms_3": 74, "rooms_4": 16}, {"name": "03-16", "rooms_1": 79, "rooms_2": 194, "rooms_3": 69, "rooms_4": 20}, {"name": "03-23", "rooms_1": 111, "rooms_2": 371, "rooms_3": 148, "rooms_4": 28}, {"name": "03-30", "rooms_1": 173, "rooms_2": 473, "rooms_3": 172, "rooms_4": 31}, {"name": "04-06", "rooms_1": 213, "rooms_2": 571, "rooms_3": 192, "rooms_4": 37}]